bigdata_cole_framework/__init__.py
bigdata_cole_framework/number_algorithms.py
bigdata_cole_framework-0.2.0.dist-info/METADATA
bigdata_cole_framework-0.2.0.dist-info/WHEEL
bigdata_cole_framework-0.2.0.dist-info/top_level.txt
bigdata_cole_framework-0.2.0.dist-info/RECORD
